get_pop/__init__.py
get_pop/cli.py
get_pop/definitions.py
get_pop/get_pop.py
get_pop/logs/__init__.py
get_pop/logs/config/__init__.py
get_pop/logs/config/logging.py
get_pop/logs/config/logging.yaml
get_pop/modules/__init__.py
get_pop/modules/helper/__init__.py
get_pop/modules/helper/misc.py
get_pop/modules/helper/move.py
get_pop/modules/helper/time.py
get_pop/modules/init/__init__.py
get_pop/modules/init/init_program.py
get_pop/modules/init/pandas_opts.py
get_pop/modules/parse/__init__.py
get_pop/modules/parse/helpers.py
get_pop/modules/parse/parse.py
get_pop/modules/save/__init__.py
get_pop/modules/save/save_csv.py
get_pop/static/__init__.py
get_pop/static/constants.py
get_pop/static/usa_pop_counties_2019.csv
get_pop-1.94.8.dist-info/LICENSE
get_pop-1.94.8.dist-info/METADATA
get_pop-1.94.8.dist-info/WHEEL
get_pop-1.94.8.dist-info/entry_points.txt
get_pop-1.94.8.dist-info/top_level.txt
get_pop-1.94.8.dist-info/RECORD
