Metadata-Version: 2.1
Name: get-pop
Version: 1.94.8
Summary: A python command line utility that generates CSVs of county-level population data for specified US states.
Home-page: UNKNOWN
Author: DSR
License: MIT
Keywords: population csv geography usa counties
Platform: UNKNOWN
Classifier: Development Status :: 5 - Production/Stable
Classifier: Intended Audience :: Developers
Classifier: Natural Language :: English
Classifier: Programming Language :: Python
Classifier: Programming Language :: Python :: 3.6
Requires-Dist: pyyaml
Requires-Dist: python-dotenv
Requires-Dist: pandas
Requires-Dist: iso8601
Requires-Dist: click
Requires-Dist: mypy-extensions
